.bumpversion.cfg
.gitignore
CHANGELOG.md
MANIFEST.in
README.md
justfile
requirements-dev.txt
requirements-flake8.txt
requirements.txt
setup.py
template-version.txt
tox.ini
.githooks/prepare-commit-msg
src/fhs_mediafiles_manager/__init__.py
src/fhs_mediafiles_manager/__version__.py
src/fhs_mediafiles_manager/cli.py
src/fhs_mediafiles_manager/date_funcs.py
src/fhs_mediafiles_manager/fhs_mediafiles_manager.py
src/fhs_mediafiles_manager/move_media.py
src/fhs_mediafiles_manager.egg-info/PKG-INFO
src/fhs_mediafiles_manager.egg-info/SOURCES.txt
src/fhs_mediafiles_manager.egg-info/dependency_links.txt
src/fhs_mediafiles_manager.egg-info/entry_points.txt
src/fhs_mediafiles_manager.egg-info/requires.txt
src/fhs_mediafiles_manager.egg-info/top_level.txt
tests/test_sample.py