Metadata-Version: 2.1
Name: fhs-mediafiles-manager
Version: 0.8.2
Summary: mediafiles manager
Home-page: https://github.com/foxhunt72/fhs-mediafiles-manager
Author: Richard de Vos
Author-email: rdevos72@gmail.com
License: MIT license
Classifier: Development Status :: 5 - Production/Stable
Classifier: Programming Language :: Python
Classifier: Programming Language :: Python :: 3
Classifier: Programming Language :: Python :: 3.6
Classifier: Programming Language :: Python :: 3.7
Classifier: Programming Language :: Python :: 3.8
Classifier: Programming Language :: Python :: 3.9
Classifier: Programming Language :: Python :: 3.10
